README.md
setup.py
DocumsAwesomeListPlugin.egg-info/PKG-INFO
DocumsAwesomeListPlugin.egg-info/SOURCES.txt
DocumsAwesomeListPlugin.egg-info/dependency_links.txt
DocumsAwesomeListPlugin.egg-info/entry_points.txt
DocumsAwesomeListPlugin.egg-info/requires.txt
DocumsAwesomeListPlugin.egg-info/top_level.txt
docums_awesome_list_plugin/__init__.py
docums_awesome_list_plugin/awesomelist.py