Metadata-Version: 2.1
Name: DocumsAwesomeListPlugin
Version: 0.1.0
Summary: Docums Plugin to inject social media cards for each entry in an awesome-list.
Home-page: https://github.com/khanhduy1407/docums-awesome-list-plugin
Author: NKDuy
Author-email: kn145660@gmail.com
License: MIT license
Keywords: docums,plugin,awesome,list
Platform: UNKNOWN
Classifier: Development Status :: 4 - Beta
Classifier: License :: OSI Approved :: MIT License
Classifier: Programming Language :: Python :: 3
Classifier: Programming Language :: Python :: 3.4
Classifier: Programming Language :: Python :: 3.5
Classifier: Programming Language :: Python :: 3.6
Classifier: Programming Language :: Python :: 3.7
Requires-Python: >=3.4, <4
